{
    "log": {
        "version": "1.2",
        "creator": {
            "name": "Ghost Synthetic Har Generator",
            "version": "1.0"
        },
        "entries": [
            {
                "request": {
                    "method": "POST",
                    "url": "https://yoursite.com/ghost/api/admin/recommendations/",
                    "headers": [
                        {
                            "name": "host",
                            "value": "127.0.0.1:2369"
                        },
                        {
                            "name": "origin",
                            "value": "http://127.0.0.1:2369"
                        }
                    ],
                    "cookies": [],
                    "queryString": [],
                    "postData": {
                        "mimeType": "application/json; charset=utf-8",
                        "text": "{\"recommendations\":[{\"title\":\"Dog Pictures\",\"url\":\"https://dogpictures.com\"}]}"
                    }
                },
                "response": {
                    "status": 201,
                    "headers": [
                        {
                            "name": "x-powered-by",
                            "value": "Express"
                        },
                        {
                            "name": "content-version",
                            "value": "v5.65"
                        },
                        {
                            "name": "vary",
                            "value": "Accept-Version, Origin, Accept-Encoding"
                        },
                        {
                            "name": "cache-control",
                            "value": "no-cache, private, no-store, must-revalidate, max-stale=0, post-check=0, pre-check=0"
                        },
                        {
                            "name": "access-control-allow-origin",
                            "value": "http://127.0.0.1:2369"
                        },
                        {
                            "name": "x-cache-invalidate",
                            "value": "/*"
                        },
                        {
                            "name": "location",
                            "value": "http://127.0.0.1:2369/ghost/api/admin/recommendations/6515dfe97c9d0336f50dc43d/"
                        },
                        {
                            "name": "content-type",
                            "value": "application/json; charset=utf-8"
                        },
                        {
                            "name": "content-length",
                            "value": "263"
                        },
                        {
                            "name": "etag",
                            "value": "W/\"107-U1yVQnK9RHRpsQp8OmKZFrS+JA4\""
                        }
                    ],
                    "content": {
                        "mimeType": "application/json; charset=utf-8",
                        "size": "263",
                        "text": "{\"recommendations\":[{\"id\":\"6515dfe97c9d0336f50dc43d\",\"title\":\"Dog Pictures\",\"reason\":null,\"excerpt\":null,\"featured_image\":null,\"favicon\":null,\"url\":\"https://dogpictures.com/\",\"one_click_subscribe\":false,\"created_at\":\"2023-09-28T20:19:53.000Z\",\"updated_at\":null}]}"
                    }
                }
            }
        ]
    }
}